{
  "description": "Contoh request body untuk Emission Prediction Endpoint",
  "endpoint": "POST /api/v1/emission/predict-hourly",
  "example_1_normal_driving": {
    "speed_mean": 45.5,
    "speed_max": 80.0,
    "speed_std": 15.2,
    "distance_delta_total": 50.0,
    "rpm_mean": 1500,
    "rpm_max": 2500,
    "engine_load_mean": 45.0,
    "is_moving_mean": 0.85,
    "is_idle_total": 9,
    "hour": 14,
    "day_of_week": 2,
    "is_weekend": 0
  },
  "example_2_high_emission_driving": {
    "speed_mean": 80.0,
    "speed_max": 120.0,
    "speed_std": 25.0,
    "distance_delta_total": 95.0,
    "rpm_mean": 2200,
    "rpm_max": 3000,
    "engine_load_mean": 75.0,
    "is_moving_mean": 0.95,
    "is_idle_total": 3,
    "hour": 18,
    "day_of_week": 4,
    "is_weekend": 0
  },
  "example_3_city_driving_with_traffic": {
    "speed_mean": 25.0,
    "speed_max": 50.0,
    "speed_std": 12.0,
    "distance_delta_total": 20.0,
    "rpm_mean": 1200,
    "rpm_max": 2000,
    "engine_load_mean": 35.0,
    "is_moving_mean": 0.60,
    "is_idle_total": 24,
    "hour": 8,
    "day_of_week": 1,
    "is_weekend": 0
  },
  "example_4_weekend_leisure_driving": {
    "speed_mean": 60.0,
    "speed_max": 100.0,
    "speed_std": 20.0,
    "distance_delta_total": 80.0,
    "rpm_mean": 1800,
    "rpm_max": 2600,
    "engine_load_mean": 50.0,
    "is_moving_mean": 0.90,
    "is_idle_total": 6,
    "hour": 15,
    "day_of_week": 5,
    "is_weekend": 1
  },
  "example_5_mostly_idle": {
    "speed_mean": 5.0,
    "speed_max": 20.0,
    "speed_std": 8.0,
    "distance_delta_total": 5.0,
    "rpm_mean": 800,
    "rpm_max": 1500,
    "engine_load_mean": 20.0,
    "is_moving_mean": 0.20,
    "is_idle_total": 48,
    "hour": 12,
    "day_of_week": 3,
    "is_weekend": 0
  },
  "feature_descriptions": {
    "speed_mean": "Rata-rata kecepatan dalam 1 jam (km/h) - Range: 0-200",
    "speed_max": "Kecepatan maksimum dalam 1 jam (km/h) - Range: 0-200",
    "speed_std": "Standar deviasi kecepatan - Range: 0-100",
    "distance_delta_total": "Total jarak tempuh dalam 1 jam (km) - Range: 0-200",
    "rpm_mean": "Rata-rata RPM dalam 1 jam - Range: 0-3000",
    "rpm_max": "RPM maksimum dalam 1 jam - Range: 0-3000",
    "engine_load_mean": "Rata-rata engine load dalam 1 jam (%) - Range: 0-100",
    "is_moving_mean": "Proporsi waktu bergerak dalam 1 jam (0-1) - Range: 0-1",
    "is_idle_total": "Total durasi idle dalam 1 jam (menit) - Range: 0-60",
    "hour": "Jam dalam sehari (0-23) - Range: 0-23",
    "day_of_week": "Hari dalam seminggu (0=Senin, 6=Minggu) - Range: 0-6",
    "is_weekend": "Apakah hari weekend (0=weekday, 1=weekend) - Range: 0-1"
  },
  "tips": {
    "note_1": "Semua nilai harus numerik (float atau int)",
    "note_2": "Pastikan nilai-nilai sesuai dengan range yang ditunjukkan",
    "note_3": "hour: 0=00:00-01:00, 14=14:00-15:00, 23=23:00-24:00",
    "note_4": "day_of_week: 0=Monday, 1=Tuesday, ..., 6=Sunday",
    "note_5": "is_moving_mean adalah proporsi (antara 0-1), bukan persentase"
  }
}
